gddriver/__init__.py
gddriver/base.py
gddriver/config.py
gddriver/errors.py
gddriver/models.py
gddriver/providers.py
gddriver/transmission.py
gddriver/drivers/__init__.py
gddriver/drivers/ftp.py
gddriver/drivers/oss.py
gddriver/drivers/s3.py
gddriver/sts/__init__.py
gddriver/sts/base.py
gddriver/sts/models.py
gddriver/sts/oss.py
gddriver/sts/s3.py
gddriver/sts/wcs.py
gddriver/utils/__init__.py
gddriver/utils/io.py
gddriver/utils/time.py
gddriver-0.2.14.dist-info/LICENSE
gddriver-0.2.14.dist-info/METADATA
gddriver-0.2.14.dist-info/WHEEL
gddriver-0.2.14.dist-info/pbr.json
gddriver-0.2.14.dist-info/top_level.txt
gddriver-0.2.14.dist-info/RECORD
